kubecfg/__main__.py
kubecfg/config.py
kubecfg/version.py
kubecfg/cli/main.py
kubecfg/cli/ping.py
kubecfg/cli/show.py
tests/test_version.py
kubecfg-0.0.4.dist-info/LICENSE
kubecfg-0.0.4.dist-info/METADATA
kubecfg-0.0.4.dist-info/WHEEL
kubecfg-0.0.4.dist-info/entry_points.txt
kubecfg-0.0.4.dist-info/top_level.txt
kubecfg-0.0.4.dist-info/RECORD
