Metadata-Version: 2.1
Name: kubecfg
Version: 0.0.4
Summary: Python library and cli utility to check k8s client configurations
Home-page: https://github.com/joaompinto/kubecfg
Author: João Pinto
Author-email: lamego.pinto@gmail.com
License: MIT
Platform: UNKNOWN
License-File: LICENSE
Requires-Dist: httpx
Requires-Dist: metadict
Requires-Dist: rich
Requires-Dist: pyyaml
Requires-Dist: typer
